hof/__init__.py
hof/cmd.py
hof-1.0.1.dist-info/METADATA
hof-1.0.1.dist-info/WHEEL
hof-1.0.1.dist-info/entry_points.txt
hof-1.0.1.dist-info/top_level.txt
hof-1.0.1.dist-info/RECORD
